cobel/__init__.py
cobel/agent/__init__.py
cobel/agent/adqn.py
cobel/agent/agent.py
cobel/agent/anet.py
cobel/agent/dqn.py
cobel/agent/dyna_q.py
cobel/agent/mfec.py
cobel/agent/pma.py
cobel/agent/q.py
cobel/agent/rw.py
cobel/agent/sfma.py
cobel/agent/sr.py
cobel/analysis/__init__.py
cobel/analysis/behavior_spatial.py
cobel/analysis/network_spatial.py
cobel/analysis/utils.py
cobel/interface/__init__.py
cobel/interface/continuous.py
cobel/interface/gridworld.py
cobel/interface/interface.py
cobel/interface/sequence.py
cobel/interface/simulator/__init__.py
cobel/interface/simulator/godot.py
cobel/interface/simulator/offline.py
cobel/interface/simulator/simulator.py
cobel/interface/simulator/unity.py
cobel/interface/topology.py
cobel/memory/__init__.py
cobel/memory/adqn.py
cobel/memory/dqn.py
cobel/memory/dyna_q.py
cobel/memory/pma.py
cobel/memory/sfma.py
cobel/memory/utils/__init__.py
cobel/memory/utils/metrics.py
cobel/misc/__init__.py
cobel/misc/continuous_tools.py
cobel/misc/gridworld_export.py
cobel/misc/gridworld_gui.py
cobel/misc/gridworld_tools.py
cobel/misc/topology_tools.py
cobel/misc/visualization.py
cobel/monitor/__init__.py
cobel/monitor/behavior.py
cobel/monitor/monitor.py
cobel/monitor/network.py
cobel/network/__init__.py
cobel/network/network.py
cobel/network/network_flax.py
cobel/network/network_tensorflow.py
cobel/network/network_torch.py
cobel/optimizer/__init__.py
cobel/optimizer/evolution.py
cobel/optimizer/grid_search.py
cobel/optimizer/optimizer.py
cobel/policy/__init__.py
cobel/policy/greedy.py
cobel/policy/policy.py
cobel/policy/random.py
cobel/policy/scalar.py
cobel/policy/softmax.py
cobel/py.typed
cobel/typing/__init__.py
cobel-3.0.0.dist-info/licenses/LICENSE
cobel-3.0.0.dist-info/WHEEL
cobel-3.0.0.dist-info/entry_points.txt
cobel-3.0.0.dist-info/METADATA
cobel-3.0.0.dist-info/RECORD
