Metadata-Version: 2.4
Name: cobel
Version: 3.0.0
Summary: Closed-loop simulator of complex behavior and learning based on reinforcement learning and deep neural networks.
Keywords: reinforcement learning,neuroscience,simulation
Author: Sen Cheng, Nicolas Diekmann, Sandhiya Vijayabaskaran, Xiangshuai Zeng, Jon Recalde, Thomas Walther
Author-email: Sen Cheng <sen.cheng@rub.de>, Nicolas Diekmann <nicolas.diekmann@rub.de>, Sandhiya Vijayabaskaran <sandhiya.vijayabaskaran@rub.de>, Xiangshuai Zeng <xiangshuai.zeng@rub.de>, Jon Recalde <jon.recaldefeo@rub.de>
License-Expression: GPL-3.0-or-later
License-File: LICENSE
Classifier: Development Status :: 5 - Production/Stable
Classifier: Intended Audience :: Education
Classifier: Intended Audience :: Science/Research
Classifier: License :: OSI Approved :: GNU General Public License v3 or later (GPLv3+)
Classifier: Programming Language :: Python :: 3.11
Classifier: Programming Language :: Python :: 3.12
Classifier: Programming Language :: Python :: 3.13
Classifier: Operating System :: OS Independent
Classifier: Topic :: Scientific/Engineering :: Artificial Intelligence
Classifier: Typing :: Typed
Requires-Dist: numpy>=2.0.0
Requires-Dist: gymnasium>=0.28.0
Requires-Dist: shapely>=2.0.0
Requires-Dist: scikit-learn>=1.2.2
Requires-Dist: pyqtgraph
Requires-Dist: pyqt6
Requires-Dist: scipy
Requires-Dist: opencv-python-headless>=4.7.0.0
Requires-Dist: flax>=0.11.0 ; extra == 'flax-cpu'
Requires-Dist: jax[cuda12] ; extra == 'flax-cuda'
Requires-Dist: flax>=0.11.0 ; extra == 'flax-cuda'
Requires-Dist: jax[tpu] ; extra == 'flax-tpu'
Requires-Dist: flax>=0.11.0 ; extra == 'flax-tpu'
Requires-Dist: tensorflow-cpu>=2.18 ; extra == 'tensorflow-cpu'
Requires-Dist: tensorflow[and-cuda]>=2.18 ; extra == 'tensorflow-cuda'
Requires-Dist: torch>=2.5.0 ; extra == 'torch'
Maintainer: Sen Cheng, Nicolas Diekmann, Sandhiya Vijayabaskaran, Jon Recalde
Maintainer-email: Sen Cheng <sen.cheng@rub.de>, Nicolas Diekmann <nicolas.diekmann@rub.de>, Sandhiya Vijayabaskaran <sandhiya.vijayabaskaran@rub.de>, Jon Recalde <jon.recaldefeo@rub.de>
Requires-Python: >=3.11
Project-URL: Homepage, https://ini.rub.de/research/groups/computational_neuroscience/
Project-URL: Repository, https://github.com/sencheng/CoBeL-RL
Provides-Extra: flax-cpu
Provides-Extra: flax-cuda
Provides-Extra: flax-tpu
Provides-Extra: tensorflow-cpu
Provides-Extra: tensorflow-cuda
Provides-Extra: torch
